{"v":"5.9.0","fr":29.9700012207031,"ip":0,"op":223,"w":500,"h":500,"nm":"Comp 3","ddd":0,"assets":[],"layers":[{"ddd":0,"ind":1,"ty":3,"nm":"Null 1","sr":1,"ks":{"o":{"a":0,"k":0,"ix":11},"r":{"a":0,"k":0,"ix":10},"p":{"a":0,"k":[-249,364,0],"ix":2,"l":2},"a":{"a":0,"k":[0,0,0],"ix":1,"l":2},"s":{"a":0,"k":[204,204,100],"ix":6,"l":2}},"ao":0,"ip":0,"op":290.000011811942,"st":0,"bm":0},{"ddd":0,"ind":2,"ty":4,"nm":"1-02 Outlines","parent":1,"sr":1,"ks":{"o":{"a":0,"k":100,"ix":11},"r":{"a":1,"k":[{"i":{"x":[0.667],"y":[1]},"o":{"x":[0.333],"y":[0]},"t":18,"s":[0]},{"i":{"x":[0.667],"y":[1]},"o":{"x":[0.167],"y":[0]},"t":39,"s":[360]},{"i":{"x":[0.833],"y":[1]},"o":{"x":[0.167],"y":[0]},"t":159,"s":[360]},{"t":176.000005946702,"s":[0]}],"ix":10},"p":{"a":1,"k":[{"i":{"x":0.575,"y":0.74},"o":{"x":0.287,"y":0.002},"t":18,"s":[241.82,-71.25,0],"to":[35.5,-76.75,0],"ti":[92.5,-1.25,0]},{"i":{"x":0.998,"y":0},"o":{"x":0.167,"y":0},"t":38,"s":[262.82,-36.75,0],"to":[-0.043,-0.097,0],"ti":[-0.269,0.409,0]},{"i":{"x":0.699,"y":0.8},"o":{"x":0.653,"y":0.227},"t":159,"s":[262.82,-36.75,0],"to":[95.769,-4.409,0],"ti":[29.674,-74.89,0]},{"t":176.000005946702,"s":[241.82,-71.25,0]}],"ix":2,"l":2},"a":{"a":0,"k":[7.5,6.5,0],"ix":1,"l":2},"s":{"a":0,"k":[261.924,261.924,100],"ix":6,"l":2}},"ao":0,"shapes":[{"ty":"gr","it":[{"ind":0,"ty":"sh","ix":1,"ks":{"a":0,"k":{"i":[[0,0],[0,0],[0.54,0.25],[0,0],[0.16,-0.07],[0,0],[-0.3,0.52],[0,0],[-0.24,-0.41]],"o":[[0,0],[0.29,0.52],[0,0],[-0.16,-0.07],[0,0],[-0.54,0.24],[0,0],[0.24,-0.41],[0,0]],"v":[[0.592,-6.074],[7.083,5.456],[6.303,6.326],[0.312,3.637],[-0.178,3.637],[-6.307,6.337],[-7.077,5.456],[-0.458,-6.083],[0.602,-6.083]],"c":true},"ix":2},"nm":"Path 1","mn":"ADBE Vector Shape - Group","hd":false},{"ty":"fl","c":{"a":1,"k":[{"i":{"x":[0.833],"y":[0.833]},"o":{"x":[0.167],"y":[0.167]},"t":36.53,"s":[0.537254929543,0.572549045086,0.694117665291,1]},{"i":{"x":[0.833],"y":[0.833]},"o":{"x":[0.167],"y":[0.167]},"t":59,"s":[0,0.600000023842,0.980392158031,1]},{"i":{"x":[0.833],"y":[0.833]},"o":{"x":[0.167],"y":[0.167]},"t":171,"s":[0,0.600000023842,0.980392158031,1]},{"t":182,"s":[0.537254929543,0.572549045086,0.694117665291,1]}],"ix":4},"o":{"a":0,"k":100,"ix":5},"r":1,"bm":0,"nm":"Fill 1","mn":"ADBE Vector Graphic - Fill","hd":false},{"ty":"tr","p":{"a":0,"k":[7.165,6.391],"ix":2},"a":{"a":0,"k":[0,0],"ix":1},"s":{"a":0,"k":[100,100],"ix":3},"r":{"a":0,"k":0,"ix":6},"o":{"a":0,"k":100,"ix":7},"sk":{"a":0,"k":0,"ix":4},"sa":{"a":0,"k":0,"ix":5},"nm":"Transform"}],"nm":"Group 1","np":4,"cix":2,"bm":0,"ix":1,"mn":"ADBE Vector Group","hd":false}],"ip":0,"op":300.00001221925,"st":0,"bm":0},{"ddd":0,"ind":3,"ty":4,"nm":"2-03 Outlines","parent":1,"sr":1,"ks":{"o":{"a":0,"k":100,"ix":11},"r":{"a":0,"k":0,"ix":10},"p":{"a":1,"k":[{"i":{"x":0.667,"y":1},"o":{"x":0.333,"y":0},"t":37,"s":[241.807,-20.5,0],"to":[0,-2.667,0],"ti":[0,2.667,0]},{"i":{"x":0.667,"y":0.667},"o":{"x":0.167,"y":0.167},"t":41,"s":[241.807,-36.5,0],"to":[0,0,0],"ti":[0,0,0]},{"i":{"x":0.833,"y":1},"o":{"x":0.167,"y":0},"t":174,"s":[241.807,-36.5,0],"to":[0,2.667,0],"ti":[0,-2.667,0]},{"t":178.000006028164,"s":[241.807,-20.5,0]}],"ix":2,"l":2},"a":{"a":0,"k":[7.5,12.8,0],"ix":1,"l":2},"s":{"a":1,"k":[{"i":{"x":[0.667,0.667,0.667],"y":[1,0.599,1]},"o":{"x":[0.333,0.333,0.333],"y":[0,0,0]},"t":35,"s":[261.924,215.048,100]},{"i":{"x":[0.667,0.667,0.667],"y":[1,1,1]},"o":{"x":[0.333,0.333,0.333],"y":[0,0.34,0]},"t":39,"s":[261.924,249.197,100]},{"i":{"x":[0.833,0.833,0.833],"y":[1,1,1]},"o":{"x":[0.333,0.333,0.333],"y":[0,0,0]},"t":44,"s":[261.924,299.532,100]},{"i":{"x":[0.833,0.833,0.833],"y":[1,1,1]},"o":{"x":[0.167,0.167,0.167],"y":[0,0,0]},"t":47,"s":[261.924,261.924,100]},{"i":{"x":[0.833,0.833,0.833],"y":[1,1,1]},"o":{"x":[0.167,0.167,0.167],"y":[0,0,0]},"t":172,"s":[261.924,261.924,100]},{"i":{"x":[0.833,0.833,0.833],"y":[1,1,1]},"o":{"x":[0.167,0.167,0.167],"y":[0,0,0]},"t":174,"s":[261.924,199.422,100]},{"i":{"x":[0.833,0.833,0.833],"y":[1,1,1]},"o":{"x":[0.333,0.333,0.333],"y":[0,0,0]},"t":180,"s":[261.924,179.89,100]},{"t":183.000006231818,"s":[261.924,215.048,100]}],"ix":6,"l":2}},"ao":0,"shapes":[{"ty":"gr","it":[{"ind":0,"ty":"sh","ix":1,"ks":{"a":0,"k":{"i":[[0.24,0.41],[0,0],[-0.54,-0.25],[0,0],[-0.16,0.07],[0,0],[0.3,-0.52],[0,0]],"o":[[0,0],[-0.29,-0.52],[0,0],[0.16,0.07],[0,0],[0.54,-0.24],[0,0],[-0.24,0.41]],"v":[[-0.597,6.083],[-7.087,-5.447],[-6.307,-6.316],[-0.317,-3.626],[0.173,-3.626],[6.313,-6.337],[7.083,-5.456],[0.463,6.083]],"c":true},"ix":2},"nm":"Path 1","mn":"ADBE Vector Shape - Group","hd":false},{"ty":"fl","c":{"a":1,"k":[{"i":{"x":[0.833],"y":[0.833]},"o":{"x":[0.167],"y":[0.167]},"t":36,"s":[0.537254929543,0.572549045086,0.694117665291,1]},{"i":{"x":[0.833],"y":[0.833]},"o":{"x":[0.167],"y":[0.167]},"t":47,"s":[0.57647061348,0.772549033165,0.996078431606,1]},{"i":{"x":[0.833],"y":[0.833]},"o":{"x":[0.167],"y":[0.167]},"t":171,"s":[0.57647061348,0.772549033165,0.996078431606,1]},{"t":182,"s":[0.537254929543,0.572549045086,0.694117665291,1]}],"ix":4},"o":{"a":0,"k":100,"ix":5},"r":1,"bm":0,"nm":"Fill 1","mn":"ADBE Vector Graphic - Fill","hd":false},{"ty":"tr","p":{"a":0,"k":[7.169,6.391],"ix":2},"a":{"a":0,"k":[0,0],"ix":1},"s":{"a":0,"k":[100,100],"ix":3},"r":{"a":0,"k":0,"ix":6},"o":{"a":0,"k":100,"ix":7},"sk":{"a":0,"k":0,"ix":4},"sa":{"a":0,"k":0,"ix":5},"nm":"Transform"}],"nm":"Group 1","np":4,"cix":2,"bm":0,"ix":1,"mn":"ADBE Vector Group","hd":false}],"ip":0,"op":300.00001221925,"st":0,"bm":0},{"ddd":0,"ind":4,"ty":4,"nm":"3-04 Outlines","parent":1,"sr":1,"ks":{"o":{"a":1,"k":[{"i":{"x":[0.833],"y":[0.833]},"o":{"x":[0.167],"y":[0.167]},"t":18,"s":[100]},{"i":{"x":[0.833],"y":[0.833]},"o":{"x":[0.167],"y":[0.167]},"t":32,"s":[0]},{"i":{"x":[0.833],"y":[0.833]},"o":{"x":[0.167],"y":[0.167]},"t":175,"s":[0]},{"t":181.000006150356,"s":[100]}],"ix":11},"r":{"a":0,"k":0,"ix":10},"p":{"a":0,"k":[241.875,-55.688,0],"ix":2,"l":2},"a":{"a":0,"k":[7.5,3.5,0],"ix":1,"l":2},"s":{"a":0,"k":[259.652,259.652,100],"ix":6,"l":2}},"ao":0,"shapes":[{"ty":"gr","it":[{"ind":0,"ty":"sh","ix":1,"ks":{"a":0,"k":{"i":[[-0.462,-0.2],[0,0],[-0.309,0.136],[0,0],[0.457,0.202],[0,0],[0.14,-0.06],[0,0]],"o":[[0,0],[0.311,0.135],[0,0],[0.457,-0.202],[0,0],[-0.139,-0.061],[0,0],[-0.462,0.2]],"v":[[-6.79,0.554],[-0.419,3.308],[0.555,3.305],[6.793,0.553],[6.793,-0.492],[0.287,-3.362],[-0.15,-3.364],[-6.79,-0.493]],"c":true},"ix":2},"nm":"Path 1","mn":"ADBE Vector Shape - Group","hd":false},{"ty":"fl","c":{"a":0,"k":[0.388235324037,0.407843167174,0.560784313725,1],"ix":4},"o":{"a":0,"k":100,"ix":5},"r":1,"bm":0,"nm":"Fill 1","mn":"ADBE Vector Graphic - Fill","hd":false},{"ty":"tr","p":{"a":0,"k":[7.136,3.408],"ix":2},"a":{"a":0,"k":[0,0],"ix":1},"s":{"a":0,"k":[100,100],"ix":3},"r":{"a":0,"k":0,"ix":6},"o":{"a":0,"k":100,"ix":7},"sk":{"a":0,"k":0,"ix":4},"sa":{"a":0,"k":0,"ix":5},"nm":"Transform"}],"nm":"Group 1","np":4,"cix":2,"bm":0,"ix":1,"mn":"ADBE Vector Group","hd":false}],"ip":0,"op":300.00001221925,"st":0,"bm":0}],"markers":[]}